[
    {
        "id": 1761,
        "page_number": 257,
        "verse_number": 11,
        "verse_key": "14:11",
        "juz_number": 13,
        "words": [
            {
                "id": 34625,
                "char_type_name": "word",
                "location": "14:11:1",
                "page_number": 257,
                "line_number": 1,
                "text_uthmani": "\u0642\u064e\u0627\u0644\u064e\u062a\u0652"
            },
            {
                "id": 34626,
                "char_type_name": "word",
                "location": "14:11:2",
                "page_number": 257,
                "line_number": 1,
                "text_uthmani": "\u0644\u064e\u0647\u064f\u0645\u0652"
            },
            {
                "id": 34627,
                "char_type_name": "word",
                "location": "14:11:3",
                "page_number": 257,
                "line_number": 1,
                "text_uthmani": "\u0631\u064f\u0633\u064f\u0644\u064f\u0647\u064f\u0645\u0652"
            },
            {
                "id": 34628,
                "char_type_name": "word",
                "location": "14:11:4",
                "page_number": 257,
                "line_number": 1,
                "text_uthmani": "\u0625\u0650\u0646"
            },
            {
                "id": 34629,
                "char_type_name": "word",
                "location": "14:11:5",
                "page_number": 257,
                "line_number": 1,
                "text_uthmani": "\u0646\u0651\u064e\u062d\u0652\u0646\u064f"
            },
            {
                "id": 34630,
                "char_type_name": "word",
                "location": "14:11:6",
                "page_number": 257,
                "line_number": 1,
                "text_uthmani": "\u0625\u0650\u0644\u0651\u064e\u0627"
            },
            {
                "id": 34631,
                "char_type_name": "word",
                "location": "14:11:7",
                "page_number": 257,
                "line_number": 1,
                "text_uthmani": "\u0628\u064e\u0634\u064e\u0631\u064c\u06ed"
            },
            {
                "id": 34632,
                "char_type_name": "word",
                "location": "14:11:8",
                "page_number": 257,
                "line_number": 1,
                "text_uthmani": "\u0645\u0651\u0650\u062b\u0652\u0644\u064f\u0643\u064f\u0645\u0652"
            },
            {
                "id": 34633,
                "char_type_name": "word",
                "location": "14:11:9",
                "page_number": 257,
                "line_number": 1,
                "text_uthmani": "\u0648\u064e\u0644\u064e\u0640\u0670\u0643\u0650\u0646\u0651\u064e"
            },
            {
                "id": 34634,
                "char_type_name": "word",
                "location": "14:11:10",
                "page_number": 257,
                "line_number": 1,
                "text_uthmani": "\u0671\u0644\u0644\u0651\u064e\u0647\u064e"
            },
            {
                "id": 34635,
                "char_type_name": "word",
                "location": "14:11:11",
                "page_number": 257,
                "line_number": 2,
                "text_uthmani": "\u064a\u064e\u0645\u064f\u0646\u0651\u064f"
            },
            {
                "id": 34636,
                "char_type_name": "word",
                "location": "14:11:12",
                "page_number": 257,
                "line_number": 2,
                "text_uthmani": "\u0639\u064e\u0644\u064e\u0649\u0670"
            },
            {
                "id": 34637,
                "char_type_name": "word",
                "location": "14:11:13",
                "page_number": 257,
                "line_number": 2,
                "text_uthmani": "\u0645\u064e\u0646"
            },
            {
                "id": 34638,
                "char_type_name": "word",
                "location": "14:11:14",
                "page_number": 257,
                "line_number": 2,
                "text_uthmani": "\u064a\u064e\u0634\u064e\u0627\u0653\u0621\u064f"
            },
            {
                "id": 34639,
                "char_type_name": "word",
                "location": "14:11:15",
                "page_number": 257,
                "line_number": 2,
                "text_uthmani": "\u0645\u0650\u0646\u0652"
            },
            {
                "id": 34640,
                "char_type_name": "word",
                "location": "14:11:16",
                "page_number": 257,
                "line_number": 2,
                "text_uthmani": "\u0639\u0650\u0628\u064e\u0627\u062f\u0650\u0647\u0650\u06e6 \u06d6"
            },
            {
                "id": 34641,
                "char_type_name": "word",
                "location": "14:11:17",
                "page_number": 257,
                "line_number": 2,
                "text_uthmani": "\u0648\u064e\u0645\u064e\u0627"
            },
            {
                "id": 34642,
                "char_type_name": "word",
                "location": "14:11:18",
                "page_number": 257,
                "line_number": 2,
                "text_uthmani": "\u0643\u064e\u0627\u0646\u064e"
            },
            {
                "id": 34643,
                "char_type_name": "word",
                "location": "14:11:19",
                "page_number": 257,
                "line_number": 2,
                "text_uthmani": "\u0644\u064e\u0646\u064e\u0627\u0653"
            },
            {
                "id": 34644,
                "char_type_name": "word",
                "location": "14:11:20",
                "page_number": 257,
                "line_number": 2,
                "text_uthmani": "\u0623\u064e\u0646"
            },
            {
                "id": 34645,
                "char_type_name": "word",
                "location": "14:11:21",
                "page_number": 257,
                "line_number": 2,
                "text_uthmani": "\u0646\u0651\u064e\u0623\u0652\u062a\u0650\u064a\u064e\u0643\u064f\u0645"
            },
            {
                "id": 34646,
                "char_type_name": "word",
                "location": "14:11:22",
                "page_number": 257,
                "line_number": 3,
                "text_uthmani": "\u0628\u0650\u0633\u064f\u0644\u0652\u0637\u064e\u0640\u0670\u0646\u064d"
            },
            {
                "id": 34647,
                "char_type_name": "word",
                "location": "14:11:23",
                "page_number": 257,
                "line_number": 3,
                "text_uthmani": "\u0625\u0650\u0644\u0651\u064e\u0627"
            },
            {
                "id": 34648,
                "char_type_name": "word",
                "location": "14:11:24",
                "page_number": 257,
                "line_number": 3,
                "text_uthmani": "\u0628\u0650\u0625\u0650\u0630\u0652\u0646\u0650"
            },
            {
                "id": 34649,
                "char_type_name": "word",
                "location": "14:11:25",
                "page_number": 257,
                "line_number": 3,
                "text_uthmani": "\u0671\u0644\u0644\u0651\u064e\u0647\u0650 \u06da"
            },
            {
                "id": 34650,
                "char_type_name": "word",
                "location": "14:11:26",
                "page_number": 257,
                "line_number": 3,
                "text_uthmani": "\u0648\u064e\u0639\u064e\u0644\u064e\u0649"
            },
            {
                "id": 34651,
                "char_type_name": "word",
                "location": "14:11:27",
                "page_number": 257,
                "line_number": 3,
                "text_uthmani": "\u0671\u0644\u0644\u0651\u064e\u0647\u0650"
            },
            {
                "id": 34652,
                "char_type_name": "word",
                "location": "14:11:28",
                "page_number": 257,
                "line_number": 3,
                "text_uthmani": "\u0641\u064e\u0644\u0652\u064a\u064e\u062a\u064e\u0648\u064e\u0643\u0651\u064e\u0644\u0650"
            },
            {
                "id": 34653,
                "char_type_name": "word",
                "location": "14:11:29",
                "page_number": 257,
                "line_number": 3,
                "text_uthmani": "\u0671\u0644\u0652\u0645\u064f\u0624\u0652\u0645\u0650\u0646\u064f\u0648\u0646\u064e"
            },
            {
                "id": 34654,
                "char_type_name": "end",
                "location": "14:11:30",
                "page_number": 257,
                "line_number": 4,
                "text_uthmani": "\u0661\u0661"
            }
        ]
    },
    {
        "id": 1762,
        "page_number": 257,
        "verse_number": 12,
        "verse_key": "14:12",
        "juz_number": 13,
        "words": [
            {
                "id": 34655,
                "char_type_name": "word",
                "location": "14:12:1",
                "page_number": 257,
                "line_number": 4,
                "text_uthmani": "\u0648\u064e\u0645\u064e\u0627"
            },
            {
                "id": 34656,
                "char_type_name": "word",
                "location": "14:12:2",
                "page_number": 257,
                "line_number": 4,
                "text_uthmani": "\u0644\u064e\u0646\u064e\u0627\u0653"
            },
            {
                "id": 34657,
                "char_type_name": "word",
                "location": "14:12:3",
                "page_number": 257,
                "line_number": 4,
                "text_uthmani": "\u0623\u064e\u0644\u0651\u064e\u0627"
            },
            {
                "id": 34658,
                "char_type_name": "word",
                "location": "14:12:4",
                "page_number": 257,
                "line_number": 4,
                "text_uthmani": "\u0646\u064e\u062a\u064e\u0648\u064e\u0643\u0651\u064e\u0644\u064e"
            },
            {
                "id": 34659,
                "char_type_name": "word",
                "location": "14:12:5",
                "page_number": 257,
                "line_number": 4,
                "text_uthmani": "\u0639\u064e\u0644\u064e\u0649"
            },
            {
                "id": 34660,
                "char_type_name": "word",
                "location": "14:12:6",
                "page_number": 257,
                "line_number": 4,
                "text_uthmani": "\u0671\u0644\u0644\u0651\u064e\u0647\u0650"
            },
            {
                "id": 34661,
                "char_type_name": "word",
                "location": "14:12:7",
                "page_number": 257,
                "line_number": 4,
                "text_uthmani": "\u0648\u064e\u0642\u064e\u062f\u0652"
            },
            {
                "id": 34662,
                "char_type_name": "word",
                "location": "14:12:8",
                "page_number": 257,
                "line_number": 4,
                "text_uthmani": "\u0647\u064e\u062f\u064e\u0649\u0670\u0646\u064e\u0627"
            },
            {
                "id": 34663,
                "char_type_name": "word",
                "location": "14:12:9",
                "page_number": 257,
                "line_number": 4,
                "text_uthmani": "\u0633\u064f\u0628\u064f\u0644\u064e\u0646\u064e\u0627 \u06da"
            },
            {
                "id": 34664,
                "char_type_name": "word",
                "location": "14:12:10",
                "page_number": 257,
                "line_number": 5,
                "text_uthmani": "\u0648\u064e\u0644\u064e\u0646\u064e\u0635\u0652\u0628\u0650\u0631\u064e\u0646\u0651\u064e"
            },
            {
                "id": 34665,
                "char_type_name": "word",
                "location": "14:12:11",
                "page_number": 257,
                "line_number": 5,
                "text_uthmani": "\u0639\u064e\u0644\u064e\u0649\u0670"
            },
            {
                "id": 34666,
                "char_type_name": "word",
                "location": "14:12:12",
                "page_number": 257,
                "line_number": 5,
                "text_uthmani": "\u0645\u064e\u0627\u0653"
            },
            {
                "id": 34667,
                "char_type_name": "word",
                "location": "14:12:13",
                "page_number": 257,
                "line_number": 5,
                "text_uthmani": "\u0621\u064e\u0627\u0630\u064e\u064a\u0652\u062a\u064f\u0645\u064f\u0648\u0646\u064e\u0627 \u06da"
            },
            {
                "id": 34668,
                "char_type_name": "word",
                "location": "14:12:14",
                "page_number": 257,
                "line_number": 5,
                "text_uthmani": "\u0648\u064e\u0639\u064e\u0644\u064e\u0649"
            },
            {
                "id": 34669,
                "char_type_name": "word",
                "location": "14:12:15",
                "page_number": 257,
                "line_number": 5,
                "text_uthmani": "\u0671\u0644\u0644\u0651\u064e\u0647\u0650"
            },
            {
                "id": 34670,
                "char_type_name": "word",
                "location": "14:12:16",
                "page_number": 257,
                "line_number": 5,
                "text_uthmani": "\u0641\u064e\u0644\u0652\u064a\u064e\u062a\u064e\u0648\u064e\u0643\u0651\u064e\u0644\u0650"
            },
            {
                "id": 34671,
                "char_type_name": "word",
                "location": "14:12:17",
                "page_number": 257,
                "line_number": 5,
                "text_uthmani": "\u0671\u0644\u0652\u0645\u064f\u062a\u064e\u0648\u064e\u0643\u0651\u0650\u0644\u064f\u0648\u0646\u064e"
            },
            {
                "id": 34672,
                "char_type_name": "end",
                "location": "14:12:18",
                "page_number": 257,
                "line_number": 6,
                "text_uthmani": "\u0661\u0662"
            }
        ]
    },
    {
        "id": 1763,
        "page_number": 257,
        "verse_number": 13,
        "verse_key": "14:13",
        "juz_number": 13,
        "words": [
            {
                "id": 34673,
                "char_type_name": "word",
                "location": "14:13:1",
                "page_number": 257,
                "line_number": 6,
                "text_uthmani": "\u0648\u064e\u0642\u064e\u0627\u0644\u064e"
            },
            {
                "id": 34674,
                "char_type_name": "word",
                "location": "14:13:2",
                "page_number": 257,
                "line_number": 6,
                "text_uthmani": "\u0671\u0644\u0651\u064e\u0630\u0650\u064a\u0646\u064e"
            },
            {
                "id": 34675,
                "char_type_name": "word",
                "location": "14:13:3",
                "page_number": 257,
                "line_number": 6,
                "text_uthmani": "\u0643\u064e\u0641\u064e\u0631\u064f\u0648\u0627\u06df"
            },
            {
                "id": 34676,
                "char_type_name": "word",
                "location": "14:13:4",
                "page_number": 257,
                "line_number": 6,
                "text_uthmani": "\u0644\u0650\u0631\u064f\u0633\u064f\u0644\u0650\u0647\u0650\u0645\u0652"
            },
            {
                "id": 34677,
                "char_type_name": "word",
                "location": "14:13:5",
                "page_number": 257,
                "line_number": 6,
                "text_uthmani": "\u0644\u064e\u0646\u064f\u062e\u0652\u0631\u0650\u062c\u064e\u0646\u0651\u064e\u0643\u064f\u0645"
            },
            {
                "id": 34678,
                "char_type_name": "word",
                "location": "14:13:6",
                "page_number": 257,
                "line_number": 6,
                "text_uthmani": "\u0645\u0651\u0650\u0646\u0652"
            },
            {
                "id": 34679,
                "char_type_name": "word",
                "location": "14:13:7",
                "page_number": 257,
                "line_number": 7,
                "text_uthmani": "\u0623\u064e\u0631\u0652\u0636\u0650\u0646\u064e\u0627\u0653"
            },
            {
                "id": 34680,
                "char_type_name": "word",
                "location": "14:13:8",
                "page_number": 257,
                "line_number": 7,
                "text_uthmani": "\u0623\u064e\u0648\u0652"
            },
            {
                "id": 34681,
                "char_type_name": "word",
                "location": "14:13:9",
                "page_number": 257,
                "line_number": 7,
                "text_uthmani": "\u0644\u064e\u062a\u064e\u0639\u064f\u0648\u062f\u064f\u0646\u0651\u064e"
            },
            {
                "id": 34682,
                "char_type_name": "word",
                "location": "14:13:10",
                "page_number": 257,
                "line_number": 7,
                "text_uthmani": "\u0641\u0650\u0649"
            },
            {
                "id": 34683,
                "char_type_name": "word",
                "location": "14:13:11",
                "page_number": 257,
                "line_number": 7,
                "text_uthmani": "\u0645\u0650\u0644\u0651\u064e\u062a\u0650\u0646\u064e\u0627 \u06d6"
            },
            {
                "id": 34684,
                "char_type_name": "word",
                "location": "14:13:12",
                "page_number": 257,
                "line_number": 7,
                "text_uthmani": "\u0641\u064e\u0623\u064e\u0648\u0652\u062d\u064e\u0649\u0670\u0653"
            },
            {
                "id": 34685,
                "char_type_name": "word",
                "location": "14:13:13",
                "page_number": 257,
                "line_number": 7,
                "text_uthmani": "\u0625\u0650\u0644\u064e\u064a\u0652\u0647\u0650\u0645\u0652"
            },
            {
                "id": 34686,
                "char_type_name": "word",
                "location": "14:13:14",
                "page_number": 257,
                "line_number": 7,
                "text_uthmani": "\u0631\u064e\u0628\u0651\u064f\u0647\u064f\u0645\u0652"
            },
            {
                "id": 34687,
                "char_type_name": "word",
                "location": "14:13:15",
                "page_number": 257,
                "line_number": 7,
                "text_uthmani": "\u0644\u064e\u0646\u064f\u0647\u0652\u0644\u0650\u0643\u064e\u0646\u0651\u064e"
            },
            {
                "id": 34688,
                "char_type_name": "word",
                "location": "14:13:16",
                "page_number": 257,
                "line_number": 8,
                "text_uthmani": "\u0671\u0644\u0638\u0651\u064e\u0640\u0670\u0644\u0650\u0645\u0650\u064a\u0646\u064e"
            },
            {
                "id": 34689,
                "char_type_name": "end",
                "location": "14:13:17",
                "page_number": 257,
                "line_number": 8,
                "text_uthmani": "\u0661\u0663"
            }
        ]
    },
    {
        "id": 1764,
        "page_number": 257,
        "verse_number": 14,
        "verse_key": "14:14",
        "juz_number": 13,
        "words": [
            {
                "id": 34690,
                "char_type_name": "word",
                "location": "14:14:1",
                "page_number": 257,
                "line_number": 8,
                "text_uthmani": "\u0648\u064e\u0644\u064e\u0646\u064f\u0633\u0652\u0643\u0650\u0646\u064e\u0646\u0651\u064e\u0643\u064f\u0645\u064f"
            },
            {
                "id": 34691,
                "char_type_name": "word",
                "location": "14:14:2",
                "page_number": 257,
                "line_number": 8,
                "text_uthmani": "\u0671\u0644\u0652\u0623\u064e\u0631\u0652\u0636\u064e"
            },
            {
                "id": 34692,
                "char_type_name": "word",
                "location": "14:14:3",
                "page_number": 257,
                "line_number": 8,
                "text_uthmani": "\u0645\u0650\u0646\u06e2"
            },
            {
                "id": 34693,
                "char_type_name": "word",
                "location": "14:14:4",
                "page_number": 257,
                "line_number": 8,
                "text_uthmani": "\u0628\u064e\u0639\u0652\u062f\u0650\u0647\u0650\u0645\u0652 \u06da"
            },
            {
                "id": 34694,
                "char_type_name": "word",
                "location": "14:14:5",
                "page_number": 257,
                "line_number": 9,
                "text_uthmani": "\u0630\u064e\u0670\u0644\u0650\u0643\u064e"
            },
            {
                "id": 34695,
                "char_type_name": "word",
                "location": "14:14:6",
                "page_number": 257,
                "line_number": 9,
                "text_uthmani": "\u0644\u0650\u0645\u064e\u0646\u0652"
            },
            {
                "id": 34696,
                "char_type_name": "word",
                "location": "14:14:7",
                "page_number": 257,
                "line_number": 9,
                "text_uthmani": "\u062e\u064e\u0627\u0641\u064e"
            },
            {
                "id": 34697,
                "char_type_name": "word",
                "location": "14:14:8",
                "page_number": 257,
                "line_number": 9,
                "text_uthmani": "\u0645\u064e\u0642\u064e\u0627\u0645\u0650\u0649"
            },
            {
                "id": 34698,
                "char_type_name": "word",
                "location": "14:14:9",
                "page_number": 257,
                "line_number": 9,
                "text_uthmani": "\u0648\u064e\u062e\u064e\u0627\u0641\u064e"
            },
            {
                "id": 34699,
                "char_type_name": "word",
                "location": "14:14:10",
                "page_number": 257,
                "line_number": 9,
                "text_uthmani": "\u0648\u064e\u0639\u0650\u064a\u062f\u0650"
            },
            {
                "id": 34700,
                "char_type_name": "end",
                "location": "14:14:11",
                "page_number": 257,
                "line_number": 9,
                "text_uthmani": "\u0661\u0664"
            }
        ]
    },
    {
        "id": 1765,
        "page_number": 257,
        "verse_number": 15,
        "verse_key": "14:15",
        "juz_number": 13,
        "words": [
            {
                "id": 34701,
                "char_type_name": "word",
                "location": "14:15:1",
                "page_number": 257,
                "line_number": 9,
                "text_uthmani": "\u0648\u064e\u0671\u0633\u0652\u062a\u064e\u0641\u0652\u062a\u064e\u062d\u064f\u0648\u0627\u06df"
            },
            {
                "id": 34702,
                "char_type_name": "word",
                "location": "14:15:2",
                "page_number": 257,
                "line_number": 10,
                "text_uthmani": "\u0648\u064e\u062e\u064e\u0627\u0628\u064e"
            },
            {
                "id": 34703,
                "char_type_name": "word",
                "location": "14:15:3",
                "page_number": 257,
                "line_number": 10,
                "text_uthmani": "\u0643\u064f\u0644\u0651\u064f"
            },
            {
                "id": 34704,
                "char_type_name": "word",
                "location": "14:15:4",
                "page_number": 257,
                "line_number": 10,
                "text_uthmani": "\u062c\u064e\u0628\u0651\u064e\u0627\u0631\u064d"
            },
            {
                "id": 34705,
                "char_type_name": "word",
                "location": "14:15:5",
                "page_number": 257,
                "line_number": 10,
                "text_uthmani": "\u0639\u064e\u0646\u0650\u064a\u062f\u064d\u06e2"
            },
            {
                "id": 34706,
                "char_type_name": "end",
                "location": "14:15:6",
                "page_number": 257,
                "line_number": 10,
                "text_uthmani": "\u0661\u0665"
            }
        ]
    },
    {
        "id": 1766,
        "page_number": 257,
        "verse_number": 16,
        "verse_key": "14:16",
        "juz_number": 13,
        "words": [
            {
                "id": 34707,
                "char_type_name": "word",
                "location": "14:16:1",
                "page_number": 257,
                "line_number": 10,
                "text_uthmani": "\u0645\u0651\u0650\u0646"
            },
            {
                "id": 34708,
                "char_type_name": "word",
                "location": "14:16:2",
                "page_number": 257,
                "line_number": 10,
                "text_uthmani": "\u0648\u064e\u0631\u064e\u0627\u0653\u0626\u0650\u0647\u0650\u06e6"
            },
            {
                "id": 34709,
                "char_type_name": "word",
                "location": "14:16:3",
                "page_number": 257,
                "line_number": 10,
                "text_uthmani": "\u062c\u064e\u0647\u064e\u0646\u0651\u064e\u0645\u064f"
            },
            {
                "id": 34710,
                "char_type_name": "word",
                "location": "14:16:4",
                "page_number": 257,
                "line_number": 10,
                "text_uthmani": "\u0648\u064e\u064a\u064f\u0633\u0652\u0642\u064e\u0649\u0670"
            },
            {
                "id": 34711,
                "char_type_name": "word",
                "location": "14:16:5",
                "page_number": 257,
                "line_number": 11,
                "text_uthmani": "\u0645\u0650\u0646"
            },
            {
                "id": 34712,
                "char_type_name": "word",
                "location": "14:16:6",
                "page_number": 257,
                "line_number": 11,
                "text_uthmani": "\u0645\u0651\u064e\u0627\u0653\u0621\u064d\u06e2"
            },
            {
                "id": 34713,
                "char_type_name": "word",
                "location": "14:16:7",
                "page_number": 257,
                "line_number": 11,
                "text_uthmani": "\u0635\u064e\u062f\u0650\u064a\u062f\u064d\u06e2"
            },
            {
                "id": 34714,
                "char_type_name": "end",
                "location": "14:16:8",
                "page_number": 257,
                "line_number": 11,
                "text_uthmani": "\u0661\u0666"
            }
        ]
    },
    {
        "id": 1767,
        "page_number": 257,
        "verse_number": 17,
        "verse_key": "14:17",
        "juz_number": 13,
        "words": [
            {
                "id": 34715,
                "char_type_name": "word",
                "location": "14:17:1",
                "page_number": 257,
                "line_number": 11,
                "text_uthmani": "\u064a\u064e\u062a\u064e\u062c\u064e\u0631\u0651\u064e\u0639\u064f\u0647\u064f\u06e5"
            },
            {
                "id": 34716,
                "char_type_name": "word",
                "location": "14:17:2",
                "page_number": 257,
                "line_number": 11,
                "text_uthmani": "\u0648\u064e\u0644\u064e\u0627"
            },
            {
                "id": 34717,
                "char_type_name": "word",
                "location": "14:17:3",
                "page_number": 257,
                "line_number": 11,
                "text_uthmani": "\u064a\u064e\u0643\u064e\u0627\u062f\u064f"
            },
            {
                "id": 34718,
                "char_type_name": "word",
                "location": "14:17:4",
                "page_number": 257,
                "line_number": 11,
                "text_uthmani": "\u064a\u064f\u0633\u0650\u064a\u063a\u064f\u0647\u064f\u06e5"
            },
            {
                "id": 34719,
                "char_type_name": "word",
                "location": "14:17:5",
                "page_number": 257,
                "line_number": 12,
                "text_uthmani": "\u0648\u064e\u064a\u064e\u0623\u0652\u062a\u0650\u064a\u0647\u0650"
            },
            {
                "id": 34720,
                "char_type_name": "word",
                "location": "14:17:6",
                "page_number": 257,
                "line_number": 12,
                "text_uthmani": "\u0671\u0644\u0652\u0645\u064e\u0648\u0652\u062a\u064f"
            },
            {
                "id": 34721,
                "char_type_name": "word",
                "location": "14:17:7",
                "page_number": 257,
                "line_number": 12,
                "text_uthmani": "\u0645\u0650\u0646"
            },
            {
                "id": 34722,
                "char_type_name": "word",
                "location": "14:17:8",
                "page_number": 257,
                "line_number": 12,
                "text_uthmani": "\u0643\u064f\u0644\u0651\u0650"
            },
            {
                "id": 34723,
                "char_type_name": "word",
                "location": "14:17:9",
                "page_number": 257,
                "line_number": 12,
                "text_uthmani": "\u0645\u064e\u0643\u064e\u0627\u0646\u064d\u06e2"
            },
            {
                "id": 34724,
                "char_type_name": "word",
                "location": "14:17:10",
                "page_number": 257,
                "line_number": 12,
                "text_uthmani": "\u0648\u064e\u0645\u064e\u0627"
            },
            {
                "id": 34725,
                "char_type_name": "word",
                "location": "14:17:11",
                "page_number": 257,
                "line_number": 12,
                "text_uthmani": "\u0647\u064f\u0648\u064e"
            },
            {
                "id": 34726,
                "char_type_name": "word",
                "location": "14:17:12",
                "page_number": 257,
                "line_number": 12,
                "text_uthmani": "\u0628\u0650\u0645\u064e\u064a\u0651\u0650\u062a\u064d\u06e2 \u06d6"
            },
            {
                "id": 34727,
                "char_type_name": "word",
                "location": "14:17:13",
                "page_number": 257,
                "line_number": 12,
                "text_uthmani": "\u0648\u064e\u0645\u0650\u0646"
            },
            {
                "id": 34728,
                "char_type_name": "word",
                "location": "14:17:14",
                "page_number": 257,
                "line_number": 13,
                "text_uthmani": "\u0648\u064e\u0631\u064e\u0627\u0653\u0626\u0650\u0647\u0650\u06e6"
            },
            {
                "id": 34729,
                "char_type_name": "word",
                "location": "14:17:15",
                "page_number": 257,
                "line_number": 13,
                "text_uthmani": "\u0639\u064e\u0630\u064e\u0627\u0628\u064c"
            },
            {
                "id": 34730,
                "char_type_name": "word",
                "location": "14:17:16",
                "page_number": 257,
                "line_number": 13,
                "text_uthmani": "\u063a\u064e\u0644\u0650\u064a\u0638\u064c\u06ed"
            },
            {
                "id": 34731,
                "char_type_name": "end",
                "location": "14:17:17",
                "page_number": 257,
                "line_number": 13,
                "text_uthmani": "\u0661\u0667"
            }
        ]
    },
    {
        "id": 1768,
        "page_number": 257,
        "verse_number": 18,
        "verse_key": "14:18",
        "juz_number": 13,
        "words": [
            {
                "id": 34732,
                "char_type_name": "word",
                "location": "14:18:1",
                "page_number": 257,
                "line_number": 13,
                "text_uthmani": "\u0645\u0651\u064e\u062b\u064e\u0644\u064f"
            },
            {
                "id": 34733,
                "char_type_name": "word",
                "location": "14:18:2",
                "page_number": 257,
                "line_number": 13,
                "text_uthmani": "\u0671\u0644\u0651\u064e\u0630\u0650\u064a\u0646\u064e"
            },
            {
                "id": 34734,
                "char_type_name": "word",
                "location": "14:18:3",
                "page_number": 257,
                "line_number": 13,
                "text_uthmani": "\u0643\u064e\u0641\u064e\u0631\u064f\u0648\u0627\u06df"
            },
            {
                "id": 34735,
                "char_type_name": "word",
                "location": "14:18:4",
                "page_number": 257,
                "line_number": 13,
                "text_uthmani": "\u0628\u0650\u0631\u064e\u0628\u0651\u0650\u0647\u0650\u0645\u0652 \u06d6"
            },
            {
                "id": 34736,
                "char_type_name": "word",
                "location": "14:18:5",
                "page_number": 257,
                "line_number": 14,
                "text_uthmani": "\u0623\u064e\u0639\u0652\u0645\u064e\u0640\u0670\u0644\u064f\u0647\u064f\u0645\u0652"
            },
            {
                "id": 34737,
                "char_type_name": "word",
                "location": "14:18:6",
                "page_number": 257,
                "line_number": 14,
                "text_uthmani": "\u0643\u064e\u0631\u064e\u0645\u064e\u0627\u062f\u064d"
            },
            {
                "id": 34738,
                "char_type_name": "word",
                "location": "14:18:7",
                "page_number": 257,
                "line_number": 14,
                "text_uthmani": "\u0671\u0634\u0652\u062a\u064e\u062f\u0651\u064e\u062a\u0652"
            },
            {
                "id": 34739,
                "char_type_name": "word",
                "location": "14:18:8",
                "page_number": 257,
                "line_number": 14,
                "text_uthmani": "\u0628\u0650\u0647\u0650"
            },
            {
                "id": 34740,
                "char_type_name": "word",
                "location": "14:18:9",
                "page_number": 257,
                "line_number": 14,
                "text_uthmani": "\u0671\u0644\u0631\u0651\u0650\u064a\u062d\u064f"
            },
            {
                "id": 34741,
                "char_type_name": "word",
                "location": "14:18:10",
                "page_number": 257,
                "line_number": 14,
                "text_uthmani": "\u0641\u0650\u0649"
            },
            {
                "id": 34742,
                "char_type_name": "word",
                "location": "14:18:11",
                "page_number": 257,
                "line_number": 14,
                "text_uthmani": "\u064a\u064e\u0648\u0652\u0645\u064d"
            },
            {
                "id": 34743,
                "char_type_name": "word",
                "location": "14:18:12",
                "page_number": 257,
                "line_number": 14,
                "text_uthmani": "\u0639\u064e\u0627\u0635\u0650\u0641\u064d\u06e2 \u06d6"
            },
            {
                "id": 34744,
                "char_type_name": "word",
                "location": "14:18:13",
                "page_number": 257,
                "line_number": 14,
                "text_uthmani": "\u0644\u0651\u064e\u0627"
            },
            {
                "id": 34745,
                "char_type_name": "word",
                "location": "14:18:14",
                "page_number": 257,
                "line_number": 14,
                "text_uthmani": "\u064a\u064e\u0642\u0652\u062f\u0650\u0631\u064f\u0648\u0646\u064e"
            },
            {
                "id": 34746,
                "char_type_name": "word",
                "location": "14:18:15",
                "page_number": 257,
                "line_number": 15,
                "text_uthmani": "\u0645\u0650\u0645\u0651\u064e\u0627"
            },
            {
                "id": 34747,
                "char_type_name": "word",
                "location": "14:18:16",
                "page_number": 257,
                "line_number": 15,
                "text_uthmani": "\u0643\u064e\u0633\u064e\u0628\u064f\u0648\u0627\u06df"
            },
            {
                "id": 34748,
                "char_type_name": "word",
                "location": "14:18:17",
                "page_number": 257,
                "line_number": 15,
                "text_uthmani": "\u0639\u064e\u0644\u064e\u0649\u0670"
            },
            {
                "id": 34749,
                "char_type_name": "word",
                "location": "14:18:18",
                "page_number": 257,
                "line_number": 15,
                "text_uthmani": "\u0634\u064e\u0649\u0652\u0621\u064d\u06e2 \u06da"
            },
            {
                "id": 34750,
                "char_type_name": "word",
                "location": "14:18:19",
                "page_number": 257,
                "line_number": 15,
                "text_uthmani": "\u0630\u064e\u0670\u0644\u0650\u0643\u064e"
            },
            {
                "id": 34751,
                "char_type_name": "word",
                "location": "14:18:20",
                "page_number": 257,
                "line_number": 15,
                "text_uthmani": "\u0647\u064f\u0648\u064e"
            },
            {
                "id": 34752,
                "char_type_name": "word",
                "location": "14:18:21",
                "page_number": 257,
                "line_number": 15,
                "text_uthmani": "\u0671\u0644\u0636\u0651\u064e\u0644\u064e\u0640\u0670\u0644\u064f"
            },
            {
                "id": 34753,
                "char_type_name": "word",
                "location": "14:18:22",
                "page_number": 257,
                "line_number": 15,
                "text_uthmani": "\u0671\u0644\u0652\u0628\u064e\u0639\u0650\u064a\u062f\u064f"
            },
            {
                "id": 34754,
                "char_type_name": "end",
                "location": "14:18:23",
                "page_number": 257,
                "line_number": 15,
                "text_uthmani": "\u0661\u0668"
            }
        ]
    }
]